paddle_fl/__init__.py
paddle_fl/mpc/__init__.py
paddle_fl/mpc/backward.py
paddle_fl/mpc/data.py
paddle_fl/mpc/framework.py
paddle_fl/mpc/initializer.py
paddle_fl/mpc/input.py
paddle_fl/mpc/io.py
paddle_fl/mpc/metrics.py
paddle_fl/mpc/mpc_init.py
paddle_fl/mpc/mpc_layer_helper.py
paddle_fl/mpc/optimizer.py
paddle_fl/mpc/version.py
paddle_fl/mpc/data_utils/__init__.py
paddle_fl/mpc/data_utils/alignment.py
paddle_fl/mpc/data_utils/data_utils.py
paddle_fl/mpc/data_utils/one_hot_encoding.py
paddle_fl/mpc/data_utils/op_extra_desc.py
paddle_fl/mpc/layers/__init__.py
paddle_fl/mpc/layers/basic.py
paddle_fl/mpc/layers/compare.py
paddle_fl/mpc/layers/conv.py
paddle_fl/mpc/layers/math.py
paddle_fl/mpc/layers/matrix.py
paddle_fl/mpc/layers/metric_op.py
paddle_fl/mpc/layers/ml.py
paddle_fl/mpc/layers/mpc_math_op_patch.py
paddle_fl/mpc/layers/rnn.py
paddle_fl/mpc/layers/tensor.py
paddle_fl/mpc/libs/libpaddle_enc.so
paddle_fl/mpc/libs/libpsi.so
paddle_fl/mpc/libs/mpc_data_utils.so
paddle_fl/mpc/libs/third_party/libaddress_sorting.a
paddle_fl/mpc/libs/third_party/libcrypto.a
paddle_fl/mpc/libs/third_party/libcrypto.so
paddle_fl/mpc/libs/third_party/libcrypto.so.1.0.0
paddle_fl/mpc/libs/third_party/libgloo.a
paddle_fl/mpc/libs/third_party/libgpr.a
paddle_fl/mpc/libs/third_party/libgrpc++.a
paddle_fl/mpc/libs/third_party/libgrpc++_cronet.a
paddle_fl/mpc/libs/third_party/libgrpc++_error_details.a
paddle_fl/mpc/libs/third_party/libgrpc++_reflection.a
paddle_fl/mpc/libs/third_party/libgrpc++_unsecure.a
paddle_fl/mpc/libs/third_party/libgrpc.a
paddle_fl/mpc/libs/third_party/libgrpc_cronet.a
paddle_fl/mpc/libs/third_party/libgrpc_unsecure.a
paddle_fl/mpc/libs/third_party/libgrpcpp_channelz.a
paddle_fl/mpc/libs/third_party/libhiredis.a
paddle_fl/mpc/libs/third_party/libhiredis.so
paddle_fl/mpc/libs/third_party/libhiredis.so.0.13
paddle_fl/mpc/libs/third_party/libssl.a
paddle_fl/mpc/libs/third_party/libssl.so
paddle_fl/mpc/libs/third_party/libssl.so.1.0.0
paddle_fl/paddle_fl/__init__.py
paddle_fl-1.2.0.dist-info/METADATA
paddle_fl-1.2.0.dist-info/WHEEL
paddle_fl-1.2.0.dist-info/top_level.txt
paddle_fl-1.2.0.dist-info/RECORD
